deepstack/__init__.py
deepstack/core.py
tests/__init__.py
tests/test_core.py
deepstack_python-0.9.dist-info/LICENSE
deepstack_python-0.9.dist-info/METADATA
deepstack_python-0.9.dist-info/WHEEL
deepstack_python-0.9.dist-info/top_level.txt
deepstack_python-0.9.dist-info/RECORD
